Verilog/Basic/src/dff.v
/* VERILOG PRACTICE MATERIAL 

Author: Dhananjay Vijayaraghavan
Date: 18 Jan 2024
Last Modified: 18 Jan 2024

This code is written as part of practicing Verilog HDL for either interviews 
or courses. The objective is this codebase is to provide an easy, workable template 
that is flexible, yet easy to use in prototyping different examples in Verilog. 

Project: D Flip Flop. 
         Design D-FF with async active-low reset and syn active-low reset. 

FILE: dff.v
PURPOSE: Module definitions of D-FF according to the spec above. 
        
*/

module D_FF(input clk, 
            input rst,
            input d, 
            output reg q);

always @(posedge clk or negedge rst) begin
    
    if (!rst)
      q <= 0;
    else
      q <= d;

end
endmodule

module D_FF_SYNC_RST(input clk, 
                     input rst,
                     input d, 
                     output reg q);

always @(posedge clk) begin
    
    if (!rst)
      q <= 0;
    else
      q <= d;

end
endmodule

Verilog/Basic/src/dff_tb.v
/* VERILOG PRACTICE MATERIAL 

Author: Dhananjay Vijayaraghavan
Date: 18 Jan 2024
Last Modified: 18 Jan 2024

This code is written as part of practicing Verilog HDL for either interviews 
or courses. The objective is this codebase is to provide an easy, workable template 
that is flexible, yet easy to use in prototyping different examples in Verilog. 

Project: D Flip Flop. 
         Design D-FF with async active-low reset and syn active-low reset. 

FILE: dff_tb.v
PURPOSE: Testbench definitions of D-FF according to the spec above. 
        
*/

`timescale 1ps/1ps
`include "src/dff.v"

module tb_dff;
reg clk;
reg rst_n;
reg data;
wire out_data;

D_FF dff 
(
    .rst (rst_n),
    .clk (clk),
    .d (data), 
    .q (out_data)
);

localparam CLK_PERIOD = 10;
always #(CLK_PERIOD/2) clk=~clk;

initial begin
    $dumpfile("tb_dff.vcd");
    $dumpvars(0, tb_dff);
end

initial begin
    rst_n <= 0; clk <= 0;
    #1 rst_n <= 1;

    #(CLK_PERIOD*3 + 4) rst_n <= 0;

    #3 rst_n <= 1;
end

initial begin

    #(CLK_PERIOD-2) data <= 0;
    #(CLK_PERIOD*2) data <= 1;

    #(CLK_PERIOD*4) data <=  0;
    #(CLK_PERIOD*2) $finish;
end

endmodule

Verilog/Basic/tb_dff.vcd
$date
	Thu Jan 18 21:14:21 2024
$end
$version
	Icarus Verilog
$end
$timescale
	1ps
$end
$scope module tb_dff $end
$var wire 1 ! out_data $end
$var reg 1 " clk $end
$var reg 1 # data $end
$var reg 1 $ rst_n $end
$scope module dff $end
$var wire 1 " clk $end
$var wire 1 # d $end
$var wire 1 $ rst $end
$var reg 1 ! q $end
$upscope $end
$upscope $end
$enddefinitions $end
#0
$dumpvars
0$
x#
0"
0!
$end
#1
1$
#5
x!
1"
#8
0#
#10
0"
#15
0!
1"
#20
0"
#25
1"
#28
1#
#30
0"
#35
0!
0$
1"
#38
1$
#40
0"
#45
1!
1"
#50
0"
#55
1"
#60
0"
#65
1"
#68
0#
#70
0"
#75
0!
1"
